{
  "lastUpdated": "2025-07-17T00:00:46.229Z",
  "stats": {
    "users": {
      "count": 36651,
      "change": 10.3
    },
    "revenue": {
      "amount": 205639,
      "change": 11.7
    },
    "projects": {
      "count": 364,
      "change": 1.1
    },
    "tasks": {
      "count": 2123,
      "change": 11.3
    }
  },
  "activities": [
    {
      "type": "user",
      "title": "Payment received",
      "timestamp": "2025-07-17T00:00:46.229Z"
    },
    {
      "type": "message",
      "title": "Task assigned",
      "timestamp": "2025-07-16T00:01:01.617Z"
    },
    {
      "type": "payment",
      "title": "New user registered",
      "timestamp": "2025-07-15T00:00:20.488Z"
    },
    {
      "type": "project",
      "title": "Project created",
      "timestamp": "2025-07-14T00:00:10.543Z"
    },
    {
      "type": "message",
      "title": "Payment received",
      "timestamp": "2025-07-13T00:00:22.831Z"
    }
  ],
  "weeklyActivity": [
    {
      "day": "Mon",
      "value": 55
    },
    {
      "day": "Tue",
      "value": 43
    },
    {
      "day": "Wed",
      "value": 12
    },
    {
      "day": "Thu",
      "value": 82
    },
    {
      "day": "Fri",
      "value": 59
    },
    {
      "day": "Sat",
      "value": 10
    },
    {
      "day": "Sun",
      "value": 100
    }
  ],
  "performanceMetrics": [
    {
      "date": "2023-10-05",
      "value": 29
    },
    {
      "date": "2023-10-06",
      "value": 44
    },
    {
      "date": "2023-10-07",
      "value": 24
    },
    {
      "date": "2023-10-08",
      "value": 32
    },
    {
      "date": "2023-10-09",
      "value": 15
    },
    {
      "date": "2023-10-10",
      "value": 41
    },
    {
      "date": "2023-10-11",
      "value": 38
    }
  ]
}