{
  "lastUpdated": "2025-08-22T00:00:28.351Z",
  "stats": {
    "users": {
      "count": 83846,
      "change": 14.6
    },
    "revenue": {
      "amount": 356221,
      "change": 3.5
    },
    "projects": {
      "count": 375,
      "change": -3.1
    },
    "tasks": {
      "count": 2617,
      "change": 3.4
    }
  },
  "activities": [
    {
      "type": "payment",
      "title": "Task completed",
      "timestamp": "2025-08-22T00:00:28.351Z"
    },
    {
      "type": "project",
      "title": "Invoice generated",
      "timestamp": "2025-08-21T00:01:01.301Z"
    },
    {
      "type": "alert",
      "title": "System alert",
      "timestamp": "2025-08-20T00:00:50.112Z"
    },
    {
      "type": "message",
      "title": "Invoice generated",
      "timestamp": "2025-08-19T00:00:04.282Z"
    },
    {
      "type": "payment",
      "title": "System alert",
      "timestamp": "2025-08-18T00:00:43.090Z"
    }
  ],
  "weeklyActivity": [
    {
      "day": "Mon",
      "value": 10
    },
    {
      "day": "Tue",
      "value": 10
    },
    {
      "day": "Wed",
      "value": 13
    },
    {
      "day": "Thu",
      "value": 20
    },
    {
      "day": "Fri",
      "value": 69
    },
    {
      "day": "Sat",
      "value": 24
    },
    {
      "day": "Sun",
      "value": 77
    }
  ],
  "performanceMetrics": [
    {
      "date": "2023-11-10",
      "value": 40
    },
    {
      "date": "2023-11-11",
      "value": 39
    },
    {
      "date": "2023-11-12",
      "value": 37
    },
    {
      "date": "2023-11-13",
      "value": 41
    },
    {
      "date": "2023-11-14",
      "value": 20
    },
    {
      "date": "2023-11-15",
      "value": 20
    },
    {
      "date": "2023-11-16",
      "value": 22
    }
  ]
}